vul_py_utils/__init__.py
vul_py_utils/benchmark/__init__.py
vul_py_utils/config.py
vul_py_utils/constant.py
vul_py_utils/env_reader/__init__.py
vul_py_utils/exceptions/__init__.py
vul_py_utils/exceptions/custom.py
vul_py_utils/exceptions/error_code.py
vul_py_utils/firebase/__init__.py
vul_py_utils/health_check/__init__.py
vul_py_utils/image/__init__.py
vul_py_utils/log/__init__.py
vul_py_utils/log/logger.py
vul_py_utils/pickle/__init__.py
vul_py_utils/pubsub/__init__.py
vul_py_utils/redis/__init__.py
vul_py_utils/redis/keys.py
vul_py_utils/response2client/__init__.py
vul_py_utils/uuid/__init__.py
vul_py_utils-0.0.8.dist-info/METADATA
vul_py_utils-0.0.8.dist-info/WHEEL
vul_py_utils-0.0.8.dist-info/RECORD
