Metadata-Version: 2.1
Name: vul_py_utils
Version: 0.0.8
Summary: The package contains common utilities for Python projects at Vulcan Labs.
Author: Tu Pham
Author-email: tupham.dev@vulcanlabs.co
Requires-Python: >=3.11,<4.0
Classifier: Programming Language :: Python :: 3
Classifier: Programming Language :: Python :: 3.11
Classifier: Programming Language :: Python :: 3.12
Requires-Dist: fastapi (>=0.105.0,<0.106.0)
Requires-Dist: firebase-admin (>=6.3.0,<7.0.0)
Requires-Dist: google (>=3.0.0,<4.0.0)
Requires-Dist: numpy (>=1.26.2,<2.0.0)
Requires-Dist: pillow (>=10.1.0,<11.0.0)
Requires-Dist: redis (>=5.0.1,<6.0.0)
